<!DOCTYPE PATCH  SYSTEM "http://vvvv.org/versions/vvvv45beta34.2.dtd" >
   <PATCH nodename="C:\Users\leo\Documents\Code\modjlrr\vvvv\sub_modules\sol_mt\layer control\loop_controls.v4p" scrollx="0" scrolly="0">
   <NODE systemname="Group (EX9)" nodename="Group (EX9)" componentmode="Hidden" id="0">
   <BOUNDS type="Node" left="4410" top="6510" width="100" height="100">
   </BOUNDS>
   <PIN pinname="Layer 1" visible="1" slicecount="1" values="||">
   </PIN>
   <PIN pinname="Layer 2" visible="1" slicecount="1" values="||">
   </PIN>
   <PIN pinname="Layer" visible="1">
   </PIN>
   </NODE>
   <NODE nodename="IOBox (String)" componentmode="InABox" id="1" systemname="IOBox (String)">
   <BOUNDS type="Node" left="2295" top="2415" width="585" height="270">
   </BOUNDS>
   <BOUNDS type="Box" left="2295" top="2415" width="585" height="270">
   </BOUNDS>
   <PIN pinname="Input String" visible="0" slicecount="1" values="|/ loop|">
   </PIN>
   <PIN pinname="Output String" visible="0">
   </PIN>
   <PIN pinname="Show Grid" slicecount="1" values="0">
   </PIN>
   <PIN pinname="String Type" slicecount="1" values="MultiLine">
   </PIN>
   </NODE>
   <NODE systemname="Switch (Value Input)" nodename="Switch (Value Input)" componentmode="Hidden" id="2">
   <BOUNDS type="Node" left="2325" top="1995" width="100" height="100">
   </BOUNDS>
   <PIN pinname="Input 2" visible="1" slicecount="1" values="0">
   </PIN>
   <PIN pinname="Switch" visible="1">
   </PIN>
   <PIN pinname="Output" visible="1">
   </PIN>
   <PIN pinname="Input 1" slicecount="1" values="5">
   </PIN>
   </NODE>
   <NODE nodename="IOBox (Value Advanced)" componentmode="InABox" id="3" systemname="IOBox (Value Advanced)">
   <BOUNDS type="Box" left="1740" top="2295" width="480" height="480">
   </BOUNDS>
   <BOUNDS type="Node" left="1740" top="2295" width="0" height="0">
   </BOUNDS>
   <PIN pinname="Y Input Value" slicecount="1" visible="1" values="0">
   </PIN>
   <PIN pinname="Units" slicecount="1" values="||">
   </PIN>
   <PIN pinname="Precision" slicecount="1" values="4">
   </PIN>
   <PIN pinname="Value Type" slicecount="1" values="Boolean">
   </PIN>
   <PIN pinname="Behavior" slicecount="1" values="Toggle">
   </PIN>
   <PIN pinname="X Input Value" slicecount="1" values="0">
   </PIN>
   </NODE>
   <NODE systemname="ToggleButton (GUI Multitouch)" filename="%VVVV%\addonpack\lib\nodes\plugins\MTGui2d.dll" nodename="ToggleButton (GUI Multitouch)" componentmode="Hidden" id="4">
   <BOUNDS type="Node" left="5895" top="4275" width="100" height="100">
   </BOUNDS>
   <PIN pinname="Touch Id" visible="1">
   </PIN>
   <PIN pinname="Touch PositionXY" visible="1">
   </PIN>
   <PIN pinname="Is new" visible="1">
   </PIN>
   <PIN pinname="Count X" slicecount="1" values="2">
   </PIN>
   <PIN pinname="Transform Out" visible="1">
   </PIN>
   <PIN pinname="Transform In" visible="1" slicecount="1" values="||">
   </PIN>
   <PIN pinname="Size Y" slicecount="1" values="0.9">
   </PIN>
   <PIN pinname="Size X" visible="1" slicecount="1" values="0.91">
   </PIN>
   <PIN pinname="Value Output" visible="1">
   </PIN>
   <PIN pinname="Count Y" slicecount="1" values="1">
   </PIN>
   <PIN pinname="Set Value" slicecount="1" visible="1" values="0">
   </PIN>
   <PIN pinname="Value Input" visible="1" slicecount="3" values="0,0,1">
   </PIN>
   <PIN pinname="Hit" visible="1">
   </PIN>
   </NODE>
   <NODE systemname="R (Value)" nodename="R (Value)" componentmode="Hidden" id="5">
   <BOUNDS type="Node" left="8130" top="3705" width="100" height="100">
   </BOUNDS>
   <PIN pinname="Receive String" slicecount="1" values="|mouse xy|">
   </PIN>
   <PIN pinname="Input Value" visible="1">
   </PIN>
   </NODE>
   <NODE systemname="R (Value)" nodename="R (Value)" componentmode="Hidden" id="6">
   <BOUNDS type="Node" left="7020" top="3705" width="100" height="100">
   </BOUNDS>
   <PIN pinname="Receive String" slicecount="1" values="|mouse id|">
   </PIN>
   <PIN pinname="Input Value" visible="1">
   </PIN>
   </NODE>
   <NODE systemname="R (Value)" nodename="R (Value)" componentmode="Hidden" id="7">
   <BOUNDS type="Node" left="8130" top="4050" width="100" height="100">
   </BOUNDS>
   <PIN pinname="Receive String" slicecount="1" values="|mouse isnew|">
   </PIN>
   <PIN pinname="Input Value" visible="1">
   </PIN>
   </NODE>
   <NODE systemname="Transform (Transform 2d)" nodename="Transform (Transform 2d)" componentmode="Hidden" id="8">
   <BOUNDS type="Node" left="5400" top="3090" width="100" height="100">
   </BOUNDS>
   <PIN pinname="Transform Out" visible="1">
   </PIN>
   <PIN pinname="TranslateX" visible="1" slicecount="1" values="0">
   </PIN>
   <PIN pinname="TranslateY" visible="1" slicecount="1" values="0.9125">
   </PIN>
   <PIN pinname="ScaleX" slicecount="1" visible="1" values="0.28">
   </PIN>
   <PIN pinname="ScaleY" slicecount="1" values="0.17">
   </PIN>
   </NODE>
   <NODE systemname="Group (EX9)" nodename="Group (EX9)" componentmode="Hidden" id="9">
   <BOUNDS type="Node" left="5430" top="5550" width="100" height="100">
   </BOUNDS>
   <PIN pinname="Layer 1" visible="1" slicecount="1" values="||">
   </PIN>
   <PIN pinname="Layer 2" visible="1" slicecount="1" values="||">
   </PIN>
   <PIN pinname="Layer" visible="1">
   </PIN>
   </NODE>
   <NODE systemname="Quad (DX9)" nodename="Quad (DX9)" componentmode="Hidden" id="10">
   <BOUNDS type="Node" left="6030" top="4830" width="100" height="100">
   </BOUNDS>
   <PIN pinname="Transform" visible="1" slicecount="1" values="||">
   </PIN>
   <PIN pinname="Layer" visible="1">
   </PIN>
   <PIN pinname="Color" visible="1" slicecount="1" values="|1.00000,1.00000,1.00000,1.00000|">
   </PIN>
   </NODE>
   <NODE nodename="IOBox (Value Advanced)" componentmode="InABox" id="11" systemname="IOBox (Value Advanced)">
   <BOUNDS type="Box" left="6405" top="2340" width="795" height="240">
   </BOUNDS>
   <BOUNDS type="Node" left="6405" top="2340" width="0" height="0">
   </BOUNDS>
   <PIN pinname="Y Input Value" slicecount="1" visible="1" values="0.65">
   </PIN>
   <PIN pinname="Units" slicecount="1" values="||">
   </PIN>
   <PIN pinname="Precision" slicecount="1" values="4">
   </PIN>
   </NODE>
   <NODE systemname="Button (3d Quad Multitouch)" filename="%VVVV%\addonpack\lib\nodes\modules\3d\Button (3d Quad Multitouch).v4p" nodename="Button (3d Quad Multitouch)" componentmode="Hidden" id="12">
   <BOUNDS type="Node" left="11775" top="6945" width="100" height="100">
   </BOUNDS>
   <PIN pinname="XY" visible="1" slicecount="1" values="0">
   </PIN>
   <PIN pinname="Transform Quad" visible="1" slicecount="1" values="||">
   </PIN>
   <PIN pinname="Touched" visible="1">
   </PIN>
   <PIN pinname="Index of Nearest" visible="1">
   </PIN>
   </NODE>
   <NODE systemname="R (Value)" nodename="R (Value)" componentmode="Hidden" id="13">
   <BOUNDS type="Node" left="12780" top="6195" width="100" height="100">
   </BOUNDS>
   <PIN pinname="Receive String" slicecount="1" values="|mouse xy|">
   </PIN>
   <PIN pinname="Input Value" visible="1">
   </PIN>
   </NODE>
   <NODE systemname="Transform (Transform 2d)" nodename="Transform (Transform 2d)" componentmode="Hidden" id="14">
   <BOUNDS type="Node" left="10995" top="5895" width="100" height="100">
   </BOUNDS>
   <PIN pinname="Transform Out" visible="1">
   </PIN>
   <PIN pinname="ScaleX" slicecount="1" values="0.13">
   </PIN>
   <PIN pinname="TranslateX" slicecount="1" visible="1" values="-0.54">
   </PIN>
   <PIN pinname="TranslateY" slicecount="1" visible="1" values="0.3">
   </PIN>
   <PIN pinname="ScaleY" visible="1" slicecount="1" values="0.14">
   </PIN>
   </NODE>
   <NODE systemname="LinearSpread (Spreads)" nodename="LinearSpread (Spreads)" componentmode="Hidden" id="15">
   <BOUNDS type="Node" left="11865" top="5385" width="100" height="100">
   </BOUNDS>
   <PIN pinname="Output" visible="1">
   </PIN>
   <PIN pinname="Input" slicecount="1" visible="1" values="0.89">
   </PIN>
   <PIN pinname="Spread Count" slicecount="1" values="2">
   </PIN>
   <PIN pinname="Width" slicecount="1" values="0.2875">
   </PIN>
   </NODE>
   <NODE nodename="IOBox (String)" componentmode="InABox" id="16" systemname="IOBox (String)">
   <BOUNDS type="Node" left="12855" top="5145" width="1155" height="270">
   </BOUNDS>
   <BOUNDS type="Box" left="12855" top="5145" width="1155" height="270">
   </BOUNDS>
   <PIN pinname="Input String" visible="0" slicecount="1" values="|/ loop control|">
   </PIN>
   <PIN pinname="Output String" visible="0">
   </PIN>
   <PIN pinname="Show Grid" slicecount="1" values="0">
   </PIN>
   <PIN pinname="String Type" slicecount="1" values="MultiLine">
   </PIN>
   </NODE>
   <NODE systemname="Quad (DX9)" nodename="Quad (DX9)" componentmode="Hidden" id="17">
   <BOUNDS type="Node" left="10785" top="7770" width="100" height="100">
   </BOUNDS>
   <PIN pinname="Transform" visible="1" slicecount="1" values="||">
   </PIN>
   <PIN pinname="Layer" visible="1">
   </PIN>
   <PIN pinname="Color" visible="1">
   </PIN>
   </NODE>
   <NODE systemname="Group (EX9)" nodename="Group (EX9)" componentmode="Hidden" id="18">
   <BOUNDS type="Node" left="10755" top="8415" width="100" height="100">
   </BOUNDS>
   <PIN pinname="Layer 1" visible="1" slicecount="1" values="||">
   </PIN>
   <PIN pinname="Layer 2" visible="1" slicecount="1" values="||">
   </PIN>
   <PIN pinname="Layer" visible="1">
   </PIN>
   </NODE>
   <NODE nodename="IOBox (Value Advanced)" componentmode="InABox" id="19" systemname="IOBox (Value Advanced)">
   <BOUNDS type="Box" left="10755" top="4830" width="795" height="240">
   </BOUNDS>
   <BOUNDS type="Node" left="10755" top="4830" width="0" height="0">
   </BOUNDS>
   <PIN pinname="Y Input Value" slicecount="1" visible="1" values="0.17">
   </PIN>
   <PIN pinname="Units" slicecount="1" values="||">
   </PIN>
   <PIN pinname="Precision" slicecount="1" values="4">
   </PIN>
   <PIN pinname="Y Output Value" visible="1">
   </PIN>
   </NODE>
   <NODE systemname="Multiply (Value)" nodename="Multiply (Value)" componentmode="Hidden" id="20">
   <BOUNDS type="Node" left="10680" top="5250" width="100" height="100">
   </BOUNDS>
   <PIN pinname="Input 2" slicecount="1" values="0.9">
   </PIN>
   <PIN pinname="Input 1" visible="1">
   </PIN>
   <PIN pinname="Output" visible="1">
   </PIN>
   </NODE>
   <NODE systemname="Text (EX9)" filename="%VVVV%\lib\nodes\plugins\VVVV.Nodes.dll" nodename="Text (EX9)" componentmode="Hidden" id="21">
   <BOUNDS type="Node" left="2400" top="4845" width="100" height="100">
   </BOUNDS>
   <PIN pinname="Transform" visible="1" slicecount="1" values="||">
   </PIN>
   <PIN pinname="Layer" visible="1">
   </PIN>
   <PIN pinname="Font" slicecount="1" visible="1" values="Arial">
   </PIN>
   <PIN pinname="Size" slicecount="1" values="75">
   </PIN>
   <PIN pinname="Color" slicecount="1" values="|0.00000,0.00000,0.00000,1.00000|">
   </PIN>
   <PIN pinname="Text" visible="1" slicecount="1" values="vvvv">
   </PIN>
   </NODE>
   <NODE systemname="Switch (String Input)" nodename="Switch (String Input)" componentmode="Hidden" id="22">
   <BOUNDS type="Node" left="2685" top="4050" width="100" height="100">
   </BOUNDS>
   <PIN pinname="Switch" visible="1" slicecount="1" values="0">
   </PIN>
   <PIN pinname="Output" visible="1">
   </PIN>
   <PIN pinname="Input 1" visible="1" slicecount="1" values="text">
   </PIN>
   <PIN pinname="Input 2" visible="1" slicecount="1" values="text">
   </PIN>
   </NODE>
   <NODE systemname="Transform (Transform 2d)" nodename="Transform (Transform 2d)" componentmode="Hidden" id="23">
   <BOUNDS type="Node" left="3375" top="4380" width="100" height="100">
   </BOUNDS>
   <PIN pinname="Transform Out" visible="1">
   </PIN>
   <PIN pinname="Transform In" visible="1" slicecount="1" values="||">
   </PIN>
   <PIN pinname="ScaleX" visible="1" slicecount="1" values="0.49">
   </PIN>
   <PIN pinname="ScaleY" visible="1" slicecount="1" values="0.49">
   </PIN>
   </NODE>
   <NODE nodename="IOBox (Value Advanced)" componentmode="InABox" id="24" systemname="IOBox (Value Advanced)">
   <BOUNDS type="Box" left="3945" top="3780" width="795" height="240">
   </BOUNDS>
   <BOUNDS type="Node" left="3945" top="3780" width="0" height="0">
   </BOUNDS>
   <PIN pinname="Y Input Value" slicecount="1" visible="1" values="0.35">
   </PIN>
   <PIN pinname="Units" slicecount="1" values="||">
   </PIN>
   <PIN pinname="Precision" slicecount="1" values="4">
   </PIN>
   </NODE>
   <NODE nodename="IOBox (Value Advanced)" componentmode="InABox" id="25" systemname="IOBox (Value Advanced)">
   <BOUNDS type="Box" left="4215" top="4080" width="795" height="240">
   </BOUNDS>
   <BOUNDS type="Node" left="4215" top="4080" width="0" height="0">
   </BOUNDS>
   <PIN pinname="Y Input Value" slicecount="1" visible="1" values="0.49">
   </PIN>
   <PIN pinname="Units" slicecount="1" values="||">
   </PIN>
   <PIN pinname="Precision" slicecount="1" values="4">
   </PIN>
   </NODE>
   <NODE nodename="IOBox (String)" componentmode="InABox" id="26" systemname="IOBox (String)">
   <BOUNDS type="Box" left="2880" top="3270" width="465" height="525">
   </BOUNDS>
   <BOUNDS type="Node" left="2880" top="3270" width="0" height="0">
   </BOUNDS>
   <PIN pinname="Input String" slicecount="2" visible="1" values="off,dflt">
   </PIN>
   <PIN pinname="Default" slicecount="1" values="text">
   </PIN>
   <PIN pinname="File Mask" slicecount="1" values="||">
   </PIN>
   <PIN pinname="Maximum Characters" slicecount="1" values="-1">
   </PIN>
   <PIN pinname="Rows" slicecount="1" values="2">
   </PIN>
   <PIN pinname="SliceCount Mode" slicecount="1" values="ColsRowsPages">
   </PIN>
   </NODE>
   <NODE nodename="IOBox (String)" componentmode="InABox" id="27" systemname="IOBox (String)">
   <BOUNDS type="Box" left="3405" top="3270" width="465" height="525">
   </BOUNDS>
   <BOUNDS type="Node" left="3405" top="3270" width="0" height="0">
   </BOUNDS>
   <PIN pinname="Input String" slicecount="2" visible="1" values="on,bnce">
   </PIN>
   <PIN pinname="Default" slicecount="1" values="text">
   </PIN>
   <PIN pinname="File Mask" slicecount="1" values="||">
   </PIN>
   <PIN pinname="Maximum Characters" slicecount="1" values="-1">
   </PIN>
   <PIN pinname="Rows" slicecount="1" values="2">
   </PIN>
   <PIN pinname="SliceCount Mode" slicecount="1" values="ColsRowsPages">
   </PIN>
   <PIN pinname="Output String" visible="1">
   </PIN>
   </NODE>
   <NODE systemname="Text (EX9)" filename="%VVVV%\lib\nodes\plugins\VVVV.Nodes.dll" nodename="Text (EX9)" componentmode="Hidden" id="28">
   <BOUNDS type="Node" left="7980" top="6450" width="100" height="100">
   </BOUNDS>
   <PIN pinname="Transform" visible="1" slicecount="1" values="||">
   </PIN>
   <PIN pinname="Layer" visible="1">
   </PIN>
   <PIN pinname="Font" slicecount="1" visible="1" values="ProggyClean">
   </PIN>
   <PIN pinname="Size" slicecount="1" values="75">
   </PIN>
   <PIN pinname="Color" slicecount="1" values="|0.00000,0.00000,0.00000,1.00000|">
   </PIN>
   <PIN pinname="Text" visible="1" slicecount="1" values="vvvv">
   </PIN>
   </NODE>
   <NODE systemname="Transform (Transform 2d)" nodename="Transform (Transform 2d)" componentmode="Hidden" id="29">
   <BOUNDS type="Node" left="8430" top="5745" width="100" height="100">
   </BOUNDS>
   <PIN pinname="Transform Out" visible="1">
   </PIN>
   <PIN pinname="Transform In" visible="1" slicecount="1" values="||">
   </PIN>
   <PIN pinname="ScaleX" visible="1" slicecount="1" values="0.49">
   </PIN>
   <PIN pinname="ScaleY" visible="1" slicecount="1" values="0.49">
   </PIN>
   </NODE>
   <NODE nodename="IOBox (Value Advanced)" componentmode="InABox" id="30" systemname="IOBox (Value Advanced)">
   <BOUNDS type="Box" left="9000" top="5145" width="795" height="240">
   </BOUNDS>
   <BOUNDS type="Node" left="9000" top="5145" width="0" height="0">
   </BOUNDS>
   <PIN pinname="Y Input Value" slicecount="1" visible="1" values="0.44">
   </PIN>
   <PIN pinname="Units" slicecount="1" values="||">
   </PIN>
   <PIN pinname="Precision" slicecount="1" values="4">
   </PIN>
   </NODE>
   <NODE nodename="IOBox (Value Advanced)" componentmode="InABox" id="31" systemname="IOBox (Value Advanced)">
   <BOUNDS type="Box" left="9270" top="5445" width="795" height="240">
   </BOUNDS>
   <BOUNDS type="Node" left="9270" top="5445" width="0" height="0">
   </BOUNDS>
   <PIN pinname="Y Input Value" slicecount="1" visible="1" values="0.49">
   </PIN>
   <PIN pinname="Units" slicecount="1" values="||">
   </PIN>
   <PIN pinname="Precision" slicecount="1" values="4">
   </PIN>
   </NODE>
   <NODE nodename="IOBox (String)" componentmode="InABox" id="32" systemname="IOBox (String)">
   <BOUNDS type="Box" left="7665" top="5505" width="795" height="240">
   </BOUNDS>
   <BOUNDS type="Node" left="7665" top="5505" width="0" height="0">
   </BOUNDS>
   <PIN pinname="Input String" slicecount="2" visible="1" values="in,out">
   </PIN>
   <PIN pinname="Default" slicecount="1" values="vvvv">
   </PIN>
   <PIN pinname="File Mask" slicecount="1" values="||">
   </PIN>
   <PIN pinname="Maximum Characters" slicecount="1" values="-1">
   </PIN>
   <PIN pinname="SliceCount Mode" slicecount="1" values="ColsRowsPages">
   </PIN>
   <PIN pinname="Columns" slicecount="1" values="2">
   </PIN>
   </NODE>
   <NODE systemname="Select (Color)" nodename="Select (Color)" componentmode="Hidden" id="33">
   <BOUNDS type="Node" left="2715" top="6105" width="100" height="100">
   </BOUNDS>
   <PIN pinname="Select" slicecount="1" values="2">
   </PIN>
   <PIN pinname="Input" visible="1">
   </PIN>
   <PIN pinname="Output" visible="1">
   </PIN>
   </NODE>
   <NODE systemname="R (Color)" nodename="R (Color)" componentmode="Hidden" id="34">
   <BOUNDS type="Node" left="2745" top="5490" width="100" height="100">
   </BOUNDS>
   <PIN pinname="Receive String" slicecount="1" values="inactive">
   </PIN>
   <PIN pinname="Input Value" visible="1">
   </PIN>
   </NODE>
   <NODE systemname="GetSlice (Spreads)" nodename="GetSlice (Spreads)" componentmode="Hidden" id="35">
   <BOUNDS type="Node" left="3720" top="6150" width="100" height="100">
   </BOUNDS>
   <PIN pinname="Input" visible="1" slicecount="1" values="0">
   </PIN>
   <PIN pinname="Output" visible="1">
   </PIN>
   </NODE>
   <NODE systemname="R (Color)" nodename="R (Color)" componentmode="Hidden" id="36">
   <BOUNDS type="Node" left="1800" top="5535" width="100" height="100">
   </BOUNDS>
   <PIN pinname="Receive String" slicecount="1" values="active">
   </PIN>
   <PIN pinname="Input Value" visible="1">
   </PIN>
   </NODE>
   <NODE systemname="Switch (Color Input)" nodename="Switch (Color Input)" componentmode="Hidden" id="37">
   <BOUNDS type="Node" left="2760" top="6555" width="100" height="100">
   </BOUNDS>
   <PIN pinname="Switch" visible="1">
   </PIN>
   <PIN pinname="Output" visible="1">
   </PIN>
   <PIN pinname="Input 1" visible="1">
   </PIN>
   <PIN pinname="Input 2" visible="1">
   </PIN>
   </NODE>
   <NODE systemname="SetSlice (Color)" nodename="SetSlice (Color)" componentmode="Hidden" id="38">
   <BOUNDS type="Node" left="2595" top="6870" width="100" height="100">
   </BOUNDS>
   <PIN pinname="Spread" visible="1">
   </PIN>
   <PIN pinname="Input" visible="1">
   </PIN>
   <PIN pinname="Output" visible="1">
   </PIN>
   </NODE>
   <NODE systemname="R (Color)" nodename="R (Color)" componentmode="Hidden" id="39">
   <BOUNDS type="Node" left="12645" top="7740" width="100" height="100">
   </BOUNDS>
   <PIN pinname="Receive String" slicecount="1" values="inactive">
   </PIN>
   <PIN pinname="Input Value" visible="1">
   </PIN>
   </NODE>
   <NODE systemname="R (Color)" nodename="R (Color)" componentmode="Hidden" id="40">
   <BOUNDS type="Node" left="13755" top="7785" width="100" height="100">
   </BOUNDS>
   <PIN pinname="Receive String" slicecount="1" values="active">
   </PIN>
   <PIN pinname="Input Value" visible="1">
   </PIN>
   </NODE>
   <NODE systemname="Switch (Color Input)" nodename="Switch (Color Input)" componentmode="Hidden" id="41">
   <BOUNDS type="Node" left="13215" top="8430" width="100" height="100">
   </BOUNDS>
   <PIN pinname="Switch" visible="1" slicecount="1" values="0">
   </PIN>
   <PIN pinname="Output" visible="1">
   </PIN>
   <PIN pinname="Input 1" visible="1" slicecount="1" values="|0.58178,0.58178,0.58178,1.00000|">
   </PIN>
   <PIN pinname="Input 2" visible="1" slicecount="1" values="|1.00000,1.00000,1.00000,1.00000|">
   </PIN>
   </NODE>
   <NODE systemname="UDP (Network Client)" nodename="UDP (Network Client)" componentmode="Hidden" id="44">
   <BOUNDS type="Node" left="4515" top="9690" width="1485" height="270">
   </BOUNDS>
   <PIN pinname="Input" visible="1" slicecount="1" values="||">
   </PIN>
   <PIN pinname="Remote Host" slicecount="1" visible="1" values="192.168.0.103">
   </PIN>
   </NODE>
   <NODE nodename="IOBox (Value Advanced)" componentmode="InABox" id="45" systemname="IOBox (Value Advanced)">
   <BOUNDS type="Box" left="5610" top="8745" width="480" height="480">
   </BOUNDS>
   <BOUNDS type="Node" left="5610" top="8745" width="0" height="0">
   </BOUNDS>
   <PIN pinname="Y Input Value" slicecount="1" visible="1" values="1">
   </PIN>
   <PIN pinname="Units" slicecount="1" values="||">
   </PIN>
   <PIN pinname="Precision" slicecount="1" values="4">
   </PIN>
   <PIN pinname="Value Type" slicecount="1" values="Boolean">
   </PIN>
   <PIN pinname="Behavior" slicecount="1" values="Bang">
   </PIN>
   <PIN pinname="X Input Value" slicecount="1" values="0">
   </PIN>
   <PIN pinname="Columns" slicecount="1" values="2">
   </PIN>
   </NODE>
   <NODE nodename="IOBox (Value Advanced)" componentmode="InABox" id="46" systemname="IOBox (Value Advanced)">
   <BOUNDS type="Box" left="6405" top="9435" width="795" height="240">
   </BOUNDS>
   <BOUNDS type="Node" left="6405" top="9435" width="0" height="0">
   </BOUNDS>
   <PIN pinname="Y Input Value" slicecount="1" values="7001">
   </PIN>
   <PIN pinname="Units" slicecount="1" values="||">
   </PIN>
   <PIN pinname="Precision" slicecount="1" values="4">
   </PIN>
   <PIN pinname="Value Type" slicecount="1" values="Integer">
   </PIN>
   </NODE>
   <NODE id="47" nodename="IOBox (String)" componentmode="InABox" systemname="IOBox (String)" hiddenwhenlocked="0" managers="">
   <BOUNDS type="Node" left="4755" top="8670" width="480" height="270">
   </BOUNDS>
   <BOUNDS type="Box" left="4755" top="8670" width="480" height="450">
   </BOUNDS>
   <PIN pinname="Input String" visible="0" slicecount="1" pintype="Input" values="|Send&cr;&lf;v|">
   </PIN>
   <PIN pinname="Output String" visible="0" pintype="Output">
   </PIN>
   <PIN pinname="Show Grid" slicecount="1" pintype="Configuration" values="0">
   </PIN>
   <PIN pinname="String Type" slicecount="1" pintype="Configuration" values="MultiLine">
   </PIN>
   <BOUNDS type="Window" left="0" top="0" width="0" height="0">
   </BOUNDS>
   <PIN pinname="Descriptive Name" pintype="Configuration" slicecount="1" values="||">
   </PIN>
   <PIN pinname="Tag" pintype="Configuration" slicecount="1" values="||">
   </PIN>
   <PIN pinname="Pin Visibility" pintype="Configuration" slicecount="1" values="True">
   </PIN>
   <PIN pinname="SliceCount Mode" pintype="Configuration" slicecount="1" values="Input">
   </PIN>
   <PIN pinname="Columns" pintype="Configuration" slicecount="1" values="1">
   </PIN>
   <PIN pinname="Rows" pintype="Configuration" slicecount="1" values="1">
   </PIN>
   <PIN pinname="Pages" pintype="Configuration" slicecount="1" values="1">
   </PIN>
   <PIN pinname="Show SliceIndex" pintype="Configuration" slicecount="1" values="0">
   </PIN>
   <PIN pinname="Font" pintype="Configuration" slicecount="1" values="|Lucida Sans Unicode|">
   </PIN>
   <PIN pinname="Size" pintype="Configuration" slicecount="1" values="7">
   </PIN>
   <PIN pinname="Default" pintype="Configuration" slicecount="1" values="||">
   </PIN>
   <PIN pinname="File Mask" pintype="Configuration" slicecount="1" values="||">
   </PIN>
   <PIN pinname="Maximum Characters" pintype="Configuration" slicecount="1" values="-1">
   </PIN>
   <PIN pinname="Show Characters [#0..#32,#127]" pintype="Configuration" slicecount="1" values="0">
   </PIN>
   <PIN pinname="SliceOffset" pintype="Input" visible="-1" slicecount="1" values="0">
   </PIN>
   <PIN pinname="Changed" pintype="Output" visible="-1">
   </PIN>
   <PIN pinname="ID" pintype="Output" visible="-1">
   </PIN>
   </NODE>
   <NODE systemname="OSCEncoder (Network)" nodename="OSCEncoder (Network)" componentmode="Hidden" id="48">
   <BOUNDS type="Node" left="4470" top="8325" width="100" height="100">
   </BOUNDS>
   <PIN pinname="Address" visible="1" slicecount="3" values="/modvj/layer0/fft,/modvj/layer0/fft/bucket,/modvj/blend/progress">
   </PIN>
   <PIN pinname="Type Tags" visible="1">
   </PIN>
   <PIN pinname="OSCMessage" visible="1">
   </PIN>
   <PIN pinname="Arguments" visible="1" slicecount="2" values="0,1">
   </PIN>
   <PIN pinname="Spread as Bundle" slicecount="1" values="0">
   </PIN>
   </NODE>
   <NODE nodename="IOBox (String)" componentmode="InABox" id="49" systemname="IOBox (String)">
   <BOUNDS type="Box" left="4770" top="7890" width="285" height="240">
   </BOUNDS>
   <BOUNDS type="Node" left="4770" top="7890" width="0" height="0">
   </BOUNDS>
   <PIN pinname="Input String" slicecount="1" visible="1" values="s">
   </PIN>
   <PIN pinname="Default" slicecount="1" values="||">
   </PIN>
   <PIN pinname="File Mask" slicecount="1" values="||">
   </PIN>
   <PIN pinname="Maximum Characters" slicecount="1" values="-1">
   </PIN>
   </NODE>
   <NODE systemname="Change (Animation)" nodename="Change (Animation)" componentmode="Hidden" id="50">
   <BOUNDS type="Node" left="6615" top="8400" width="100" height="100">
   </BOUNDS>
   <PIN pinname="Input" visible="1" slicecount="3" values="1,0,1">
   </PIN>
   <PIN pinname="OnChange" visible="1">
   </PIN>
   </NODE>
   <NODE systemname="R (String)" nodename="R (String)" componentmode="Hidden" id="51">
   <BOUNDS type="Node" left="6630" top="9000" width="100" height="100">
   </BOUNDS>
   <PIN pinname="Receive String" slicecount="1" values="host">
   </PIN>
   <PIN pinname="Input Value" visible="1">
   </PIN>
   </NODE>
   <NODE systemname="Add (String)" nodename="Add (String)" componentmode="Hidden" id="52">
   <BOUNDS type="Node" left="2535" top="8700" width="100" height="100">
   </BOUNDS>
   <PIN pinname="Input 1" slicecount="1" visible="1" values="/modvj/blend">
   </PIN>
   <PIN pinname="Input 2" visible="1" slicecount="2" values="/progress,/choose">
   </PIN>
   <PIN pinname="Output" visible="1">
   </PIN>
   <PIN pinname="Input Count" slicecount="1" values="3">
   </PIN>
   <PIN pinname="Input 3" visible="1">
   </PIN>
   </NODE>
   <NODE nodename="IOBox (String)" componentmode="InABox" id="53" systemname="IOBox (String)">
   <BOUNDS type="Box" left="1500" top="8025" width="1155" height="240">
   </BOUNDS>
   <BOUNDS type="Node" left="1500" top="8025" width="0" height="0">
   </BOUNDS>
   <PIN pinname="Input String" slicecount="1" visible="1" values="/magi">
   </PIN>
   <PIN pinname="Default" slicecount="1" values="text">
   </PIN>
   <PIN pinname="File Mask" slicecount="1" values="||">
   </PIN>
   <PIN pinname="Maximum Characters" slicecount="1" values="-1">
   </PIN>
   </NODE>
   <NODE nodename="IOBox (String)" componentmode="InABox" id="54" systemname="IOBox (String)">
   <BOUNDS type="Box" left="3150" top="7605" width="1455" height="915">
   </BOUNDS>
   <BOUNDS type="Node" left="3150" top="7605" width="0" height="0">
   </BOUNDS>
   <PIN pinname="Input String" slicecount="2" visible="1" values="/loop/set/on_off,/loop/type">
   </PIN>
   <PIN pinname="Default" slicecount="1" values="text">
   </PIN>
   <PIN pinname="File Mask" slicecount="1" values="||">
   </PIN>
   <PIN pinname="Maximum Characters" slicecount="1" values="-1">
   </PIN>
   <PIN pinname="SliceCount Mode" slicecount="1" values="ColsRowsPages">
   </PIN>
   <PIN pinname="Rows" slicecount="1" values="2">
   </PIN>
   <PIN pinname="Output String" visible="1">
   </PIN>
   </NODE>
   <NODE nodename="IOBox (String)" componentmode="InABox" id="55" systemname="IOBox (String)">
   <BOUNDS type="Box" left="7035" top="600" width="795" height="240">
   </BOUNDS>
   <BOUNDS type="Node" left="7035" top="600" width="0" height="0">
   </BOUNDS>
   <PIN pinname="Input String" slicecount="1" visible="1" values="/layer0">
   </PIN>
   <PIN pinname="Default" slicecount="1" values="text">
   </PIN>
   <PIN pinname="File Mask" slicecount="1" values="||">
   </PIN>
   <PIN pinname="Maximum Characters" slicecount="1" values="-1">
   </PIN>
   <PIN pinname="Output String" visible="1">
   </PIN>
   <PIN pinname="Descriptive Name" slicecount="1" values="layer">
   </PIN>
   </NODE>
   <NODE systemname="Switch (String Input)" nodename="Switch (String Input)" componentmode="Hidden" id="56">
   <BOUNDS type="Node" left="6720" top="7740" width="100" height="100">
   </BOUNDS>
   <PIN pinname="Input 1" slicecount="1" visible="1" values="d">
   </PIN>
   <PIN pinname="Input 2" slicecount="1" visible="1" values="b">
   </PIN>
   <PIN pinname="Switch" visible="1">
   </PIN>
   <PIN pinname="Output" visible="1">
   </PIN>
   </NODE>
   <NODE nodename="IOBox (String)" componentmode="InABox" id="57" systemname="IOBox (String)">
   <BOUNDS type="Box" left="7035" top="7380" width="795" height="240">
   </BOUNDS>
   <BOUNDS type="Node" left="7035" top="7380" width="0" height="0">
   </BOUNDS>
   <PIN pinname="Input String" slicecount="1" visible="1" values="&apos;d&apos;">
   </PIN>
   <PIN pinname="Default" slicecount="1" values="text">
   </PIN>
   <PIN pinname="File Mask" slicecount="1" values="||">
   </PIN>
   <PIN pinname="Maximum Characters" slicecount="1" values="-1">
   </PIN>
   </NODE>
   <NODE nodename="IOBox (String)" componentmode="InABox" id="58" systemname="IOBox (String)">
   <BOUNDS type="Box" left="7335" top="7665" width="795" height="240">
   </BOUNDS>
   <BOUNDS type="Node" left="7335" top="7665" width="0" height="0">
   </BOUNDS>
   <PIN pinname="Input String" slicecount="1" visible="1" values="&apos;b&apos;">
   </PIN>
   <PIN pinname="Default" slicecount="1" values="text">
   </PIN>
   <PIN pinname="File Mask" slicecount="1" values="||">
   </PIN>
   <PIN pinname="Maximum Characters" slicecount="1" values="-1">
   </PIN>
   </NODE>
   <NODE systemname="Vector (2d Split)" nodename="Vector (2d Split)" componentmode="Hidden" id="59">
   <BOUNDS type="Node" left="5520" top="6690" width="100" height="100">
   </BOUNDS>
   <PIN pinname="XY" visible="1">
   </PIN>
   <PIN pinname="X" visible="1">
   </PIN>
   <PIN pinname="Y" visible="1">
   </PIN>
   </NODE>
   <NODE systemname="Cons (String)" filename="%VVVV%\lib\nodes\plugins\VVVV.Nodes.dll" nodename="Cons (String)" componentmode="Hidden" id="60">
   <BOUNDS type="Node" left="5535" top="7965" width="100" height="100">
   </BOUNDS>
   <PIN pinname="Input 1" visible="1" slicecount="1" values="1">
   </PIN>
   <PIN pinname="Input 2" visible="1">
   </PIN>
   <PIN pinname="Output" visible="1">
   </PIN>
   </NODE>
   <NODE nodename="IOBox (Value Advanced)" componentmode="InABox" id="77" systemname="IOBox (Value Advanced)">
   <BOUNDS type="Box" left="11460" top="1800" width="795" height="240">
   </BOUNDS>
   <BOUNDS type="Node" left="11460" top="1800" width="0" height="0">
   </BOUNDS>
   <PIN pinname="Y Input Value" slicecount="1" visible="1" values="0.89">
   </PIN>
   <PIN pinname="Units" slicecount="1" values="||">
   </PIN>
   <PIN pinname="Precision" slicecount="1" values="4">
   </PIN>
   </NODE>
   <NODE systemname="Subtract (Value)" nodename="Subtract (Value)" componentmode="Hidden" id="78">
   <BOUNDS type="Node" left="8910" top="1500" width="100" height="100">
   </BOUNDS>
   <PIN pinname="Input 2" slicecount="1" visible="1" values="0.08275">
   </PIN>
   <PIN pinname="Input 1" visible="1" slicecount="1" values="0.75">
   </PIN>
   <PIN pinname="Output" visible="1">
   </PIN>
   </NODE>
   <NODE systemname="Add (Value)" nodename="Add (Value)" componentmode="Hidden" id="79">
   <BOUNDS type="Node" left="10335" top="1575" width="100" height="100">
   </BOUNDS>
   <PIN pinname="Input 2" slicecount="1" values="0.2025">
   </PIN>
   <PIN pinname="Input 1" visible="1">
   </PIN>
   <PIN pinname="Output" visible="1">
   </PIN>
   </NODE>
   <NODE systemname="GetSlice (Spreads)" nodename="GetSlice (Spreads)" componentmode="Hidden" id="80">
   <BOUNDS type="Node" left="1515" top="1875" width="100" height="100">
   </BOUNDS>
   <PIN pinname="Output" visible="1">
   </PIN>
   <PIN pinname="Input" visible="1">
   </PIN>
   </NODE>
   <NODE id="81" systemname="IOBox (Value Advanced)" componentmode="InABox">
   <PIN pinname="Descriptive Name" slicecount="1" values="top_tag_inp">
   </PIN>
   <BOUNDS type="Box" left="960" top="575" width="750" height="240">
   </BOUNDS>
   <BOUNDS type="Node" left="960" top="575" width="750" height="240">
   </BOUNDS>
   </NODE>
   <LINK srcnodeid="81" srcpinname="Y Output Value" dstnodeid="80" dstpinname="Input">
   </LINK>
   <LINK srcnodeid="80" srcpinname="Output" dstnodeid="3" dstpinname="Y Input Value">
   </LINK>
   <LINK srcnodeid="3" srcpinname="Y Output Value" dstnodeid="2" dstpinname="Switch">
   </LINK>
   <NODE id="82" systemname="IOBox (Value Advanced)" componentmode="InABox">
   <PIN pinname="Descriptive Name" slicecount="1" values="TranslateY">
   </PIN>
   <BOUNDS type="Box" left="5295" top="545" width="750" height="240">
   </BOUNDS>
   <BOUNDS type="Node" left="5295" top="545" width="750" height="240">
   </BOUNDS>
   </NODE>
   <LINK srcnodeid="82" srcpinname="Y Output Value" dstnodeid="2" dstpinname="Input 2">
   </LINK>
   <LINK srcnodeid="23" srcpinname="Transform Out" dstnodeid="21" dstpinname="Transform">
   </LINK>
   <LINK srcnodeid="22" srcpinname="Output" dstnodeid="21" dstpinname="Text">
   </LINK>
   <LINK srcnodeid="53" srcpinname="Output String" dstnodeid="52" dstpinname="Input 1">
   </LINK>
   <LINK srcnodeid="55" srcpinname="Output String" dstnodeid="52" dstpinname="Input 2">
   </LINK>
   <LINK srcnodeid="54" srcpinname="Output String" dstnodeid="52" dstpinname="Input 3">
   </LINK>
   <LINK srcnodeid="33" srcpinname="Output" dstnodeid="38" dstpinname="Spread">
   </LINK>
   <LINK srcnodeid="37" srcpinname="Output" dstnodeid="38" dstpinname="Input">
   </LINK>
   <LINK srcnodeid="4" srcpinname="Value Output" dstnodeid="22" dstpinname="Switch">
   </LINK>
   <LINK srcnodeid="26" srcpinname="Output String" dstnodeid="22" dstpinname="Input 1">
   </LINK>
   <LINK srcnodeid="27" srcpinname="Output String" dstnodeid="22" dstpinname="Input 2">
   </LINK>
   <LINK srcnodeid="34" srcpinname="Input Value" dstnodeid="33" dstpinname="Input">
   </LINK>
   <LINK srcnodeid="35" srcpinname="Output" dstnodeid="37" dstpinname="Switch">
   </LINK>
   <LINK srcnodeid="36" srcpinname="Input Value" dstnodeid="37" dstpinname="Input 1">
   </LINK>
   <LINK srcnodeid="34" srcpinname="Input Value" dstnodeid="37" dstpinname="Input 2">
   </LINK>
   <LINK srcnodeid="4" srcpinname="Transform Out" dstnodeid="23" dstpinname="Transform In">
   </LINK>
   <LINK srcnodeid="24" srcpinname="Y Output Value" dstnodeid="23" dstpinname="ScaleX">
   </LINK>
   <LINK srcnodeid="25" srcpinname="Y Output Value" dstnodeid="23" dstpinname="ScaleY">
   </LINK>
   <LINK srcnodeid="4" srcpinname="Value Output" dstnodeid="35" dstpinname="Input">
   </LINK>
   <LINK srcnodeid="9" srcpinname="Layer" dstnodeid="0" dstpinname="Layer 1">
   </LINK>
   <LINK srcnodeid="18" srcpinname="Layer" dstnodeid="0" dstpinname="Layer 2">
   </LINK>
   <NODE id="83" systemname="IOBox (Node)" componentmode="InABox">
   <PIN pinname="Descriptive Name" slicecount="1" values="Layer">
   </PIN>
   <BOUNDS type="Box" left="4410" top="11915" width="750" height="240">
   </BOUNDS>
   <BOUNDS type="Node" left="4410" top="11915" width="750" height="240">
   </BOUNDS>
   </NODE>
   <LINK srcnodeid="0" srcpinname="Layer" dstnodeid="83" dstpinname="Input Node">
   </LINK>
   <LINK srcnodeid="52" srcpinname="Output" dstnodeid="48" dstpinname="Address">
   </LINK>
   <LINK srcnodeid="49" srcpinname="Output String" dstnodeid="48" dstpinname="Type Tags">
   </LINK>
   <LINK srcnodeid="60" srcpinname="Output" dstnodeid="48" dstpinname="Arguments">
   </LINK>
   <LINK srcnodeid="48" srcpinname="OSCMessage" dstnodeid="44" dstpinname="Input">
   </LINK>
   <LINK srcnodeid="45" srcpinname="Y Output Value" dstnodeid="44" dstpinname="Do Send">
   </LINK>
   <LINK srcnodeid="51" srcpinname="Input Value" dstnodeid="44" dstpinname="Remote Host">
   </LINK>
   <LINK srcnodeid="46" srcpinname="Y Output Value" dstnodeid="44" dstpinname="Remote Port">
   </LINK>
   <LINK srcnodeid="11" srcpinname="Y Output Value" dstnodeid="8" dstpinname="TranslateX">
   </LINK>
   <LINK srcnodeid="2" srcpinname="Output" dstnodeid="8" dstpinname="TranslateY">
   </LINK>
   <LINK srcnodeid="10" srcpinname="Layer" dstnodeid="9" dstpinname="Layer 1">
   </LINK>
   <LINK srcnodeid="21" srcpinname="Layer" dstnodeid="9" dstpinname="Layer 2">
   </LINK>
   <LINK srcnodeid="56" srcpinname="Output" dstnodeid="60" dstpinname="Input 2">
   </LINK>
   <LINK srcnodeid="4" srcpinname="Value Output" dstnodeid="59" dstpinname="XY">
   </LINK>
   <LINK srcnodeid="8" srcpinname="Transform Out" dstnodeid="4" dstpinname="Transform In">
   </LINK>
   <LINK srcnodeid="6" srcpinname="Input Value" dstnodeid="4" dstpinname="Touch Id">
   </LINK>
   <LINK srcnodeid="5" srcpinname="Input Value" dstnodeid="4" dstpinname="Touch PositionXY">
   </LINK>
   <LINK srcnodeid="7" srcpinname="Input Value" dstnodeid="4" dstpinname="Is new">
   </LINK>
   <LINK srcnodeid="4" srcpinname="Transform Out" dstnodeid="10" dstpinname="Transform">
   </LINK>
   <LINK srcnodeid="38" srcpinname="Output" dstnodeid="10" dstpinname="Color">
   </LINK>
   <LINK srcnodeid="78" srcpinname="Output" dstnodeid="11" dstpinname="Y Input Value">
   </LINK>
   <LINK srcnodeid="4" srcpinname="Value Output" dstnodeid="50" dstpinname="Input">
   </LINK>
   <LINK srcnodeid="59" srcpinname="Y" dstnodeid="56" dstpinname="Switch">
   </LINK>
   <LINK srcnodeid="57" srcpinname="Output String" dstnodeid="56" dstpinname="Input 1">
   </LINK>
   <LINK srcnodeid="58" srcpinname="Output String" dstnodeid="56" dstpinname="Input 2">
   </LINK>
   <LINK srcnodeid="29" srcpinname="Transform Out" dstnodeid="28" dstpinname="Transform">
   </LINK>
   <LINK srcnodeid="32" srcpinname="Output String" dstnodeid="28" dstpinname="Text">
   </LINK>
   <LINK srcnodeid="14" srcpinname="Transform Out" dstnodeid="29" dstpinname="Transform In">
   </LINK>
   <LINK srcnodeid="30" srcpinname="Y Output Value" dstnodeid="29" dstpinname="ScaleX">
   </LINK>
   <LINK srcnodeid="31" srcpinname="Y Output Value" dstnodeid="29" dstpinname="ScaleY">
   </LINK>
   <NODE id="84" systemname="IOBox (Value Advanced)" componentmode="InABox">
   <PIN pinname="Descriptive Name" slicecount="1" values="TranslateX">
   </PIN>
   <BOUNDS type="Box" left="3450" top="500" width="750" height="240">
   </BOUNDS>
   <BOUNDS type="Node" left="3450" top="500" width="750" height="240">
   </BOUNDS>
   </NODE>
   <LINK srcnodeid="84" srcpinname="Y Output Value" dstnodeid="78" dstpinname="Input 1">
   </LINK>
   <LINK srcnodeid="84" srcpinname="Y Output Value" dstnodeid="79" dstpinname="Input 1">
   </LINK>
   <LINK srcnodeid="19" srcpinname="Y Output Value" dstnodeid="20" dstpinname="Input 1">
   </LINK>
   <LINK srcnodeid="17" srcpinname="Layer" dstnodeid="18" dstpinname="Layer 1">
   </LINK>
   <LINK srcnodeid="28" srcpinname="Layer" dstnodeid="18" dstpinname="Layer 2">
   </LINK>
   <LINK srcnodeid="14" srcpinname="Transform Out" dstnodeid="17" dstpinname="Transform">
   </LINK>
   <LINK srcnodeid="41" srcpinname="Output" dstnodeid="17" dstpinname="Color">
   </LINK>
   <LINK srcnodeid="15" srcpinname="Output" dstnodeid="14" dstpinname="TranslateX">
   </LINK>
   <LINK srcnodeid="2" srcpinname="Output" dstnodeid="14" dstpinname="TranslateY">
   </LINK>
   <LINK srcnodeid="20" srcpinname="Output" dstnodeid="14" dstpinname="ScaleY">
   </LINK>
   <LINK srcnodeid="79" srcpinname="Output" dstnodeid="77" dstpinname="Y Input Value">
   </LINK>
   <LINK srcnodeid="14" srcpinname="Transform Out" dstnodeid="12" dstpinname="Transform Quad">
   </LINK>
   <LINK srcnodeid="13" srcpinname="Input Value" dstnodeid="12" dstpinname="XY">
   </LINK>
   <LINK srcnodeid="77" srcpinname="Y Output Value" dstnodeid="15" dstpinname="Input">
   </LINK>
   <LINK srcnodeid="12" srcpinname="Touched" dstnodeid="41" dstpinname="Switch">
   </LINK>
   <LINK srcnodeid="39" srcpinname="Input Value" dstnodeid="41" dstpinname="Input 1">
   </LINK>
   <LINK srcnodeid="40" srcpinname="Input Value" dstnodeid="41" dstpinname="Input 2">
   </LINK>
   <BOUNDS type="Window" left="2580" top="7170" width="21960" height="14025">
   </BOUNDS>
   <NODE nodename="IOBox (Value Advanced)" componentmode="InABox" id="86" systemname="IOBox (Value Advanced)">
   <BOUNDS type="Box" left="6615" top="11850" width="480" height="480">
   </BOUNDS>
   <BOUNDS type="Node" left="6615" top="11850" width="0" height="0">
   </BOUNDS>
   <PIN pinname="Units" slicecount="1" values="||">
   </PIN>
   <PIN pinname="Precision" slicecount="1" values="4">
   </PIN>
   <PIN pinname="Value Type" slicecount="1" values="Boolean">
   </PIN>
   <PIN pinname="Behavior" slicecount="1" values="Toggle">
   </PIN>
   <PIN pinname="Descriptive Name" slicecount="1" values="|tog out|">
   </PIN>
   <PIN pinname="Columns" slicecount="1" values="2">
   </PIN>
   </NODE>
   <LINK srcnodeid="4" srcpinname="Value Output" dstnodeid="86" dstpinname="Y Input Value">
   </LINK>
   <NODE nodename="IOBox (Value Advanced)" componentmode="InABox" id="87" systemname="IOBox (Value Advanced)">
   <BOUNDS type="Box" left="7935" top="11910" width="480" height="480">
   </BOUNDS>
   <BOUNDS type="Node" left="7935" top="11910" width="0" height="0">
   </BOUNDS>
   <PIN pinname="Units" slicecount="1" values="||">
   </PIN>
   <PIN pinname="Precision" slicecount="1" values="4">
   </PIN>
   <PIN pinname="Value Type" slicecount="1" values="Boolean">
   </PIN>
   <PIN pinname="Behavior" slicecount="1" values="Toggle">
   </PIN>
   <PIN pinname="Descriptive Name" slicecount="1" values="|but out|">
   </PIN>
   <PIN pinname="Rows" slicecount="1" values="1">
   </PIN>
   <PIN pinname="Columns" slicecount="1" values="2">
   </PIN>
   </NODE>
   <LINK srcnodeid="12" srcpinname="Touched" dstnodeid="87" dstpinname="Y Input Value">
   </LINK>
   <PACK Name="opencv" Version="0.2.0">
   </PACK>
   <PACK Name="addonpack" Version="34.1.0">
   </PACK>
   <NODE nodename="IOBox (Enumerations)" componentmode="InABox" id="88" systemname="IOBox (Enumerations)">
   <BOUNDS type="Box" left="10665" top="450" width="1590" height="270">
   </BOUNDS>
   <BOUNDS type="Node" left="10665" top="450" width="0" height="0">
   </BOUNDS>
   <PIN pinname="Input Enum" slicecount="1" visible="1" values="Arial">
   </PIN>
   <PIN pinname="Output Enum" visible="1">
   </PIN>
   <PIN pinname="Descriptive Name" slicecount="1" values="font">
   </PIN>
   </NODE>
   <LINK srcnodeid="88" srcpinname="Output Enum" dstnodeid="28" dstpinname="Font">
   </LINK>
   <LINK srcnodeid="88" srcpinname="Output Enum" dstnodeid="21" dstpinname="Font">
   </LINK>
   <NODE nodename="IOBox (Value Advanced)" componentmode="InABox" id="89" systemname="IOBox (Value Advanced)">
   <BOUNDS type="Box" left="12990" top="135" width="480" height="480">
   </BOUNDS>
   <BOUNDS type="Node" left="12990" top="135" width="0" height="0">
   </BOUNDS>
   <PIN pinname="Y Input Value" slicecount="1" visible="1" values="0">
   </PIN>
   <PIN pinname="Units" slicecount="1" values="||">
   </PIN>
   <PIN pinname="Precision" slicecount="1" values="4">
   </PIN>
   <PIN pinname="Value Type" slicecount="1" values="Boolean">
   </PIN>
   <PIN pinname="Behavior" slicecount="1" values="Toggle">
   </PIN>
   <PIN pinname="Descriptive Name" slicecount="1" values="set_vals">
   </PIN>
   <PIN pinname="Y Output Value" visible="1">
   </PIN>
   </NODE>
   <NODE systemname="Change (Animation)" nodename="Change (Animation)" componentmode="Hidden" id="90">
   <BOUNDS type="Node" left="13590" top="3495" width="100" height="100">
   </BOUNDS>
   <PIN pinname="Input" visible="1" slicecount="2" values="0,0.0862947925925255">
   </PIN>
   <PIN pinname="OnChange" visible="1">
   </PIN>
   </NODE>
   <LINK srcnodeid="90" srcpinname="OnChange" dstnodeid="4" dstpinname="Set Value">
   </LINK>
   <NODE systemname="UDP (Network Client)" nodename="UDP (Network Client)" componentmode="Hidden" id="107">
   <BOUNDS type="Node" left="17505" top="10320" width="1485" height="270">
   </BOUNDS>
   <PIN pinname="Input" visible="1" slicecount="1" values="||">
   </PIN>
   <PIN pinname="Remote Host" slicecount="1" visible="1" values="192.168.0.103">
   </PIN>
   <PIN pinname="Do Send" slicecount="8" visible="1" values="0,0,0,0,0,0,0,0">
   </PIN>
   </NODE>
   <NODE nodename="IOBox (Value Advanced)" componentmode="InABox" id="106" systemname="IOBox (Value Advanced)">
   <BOUNDS type="Box" left="19395" top="10065" width="795" height="240">
   </BOUNDS>
   <BOUNDS type="Node" left="19395" top="10065" width="0" height="0">
   </BOUNDS>
   <PIN pinname="Y Input Value" slicecount="1" values="7001">
   </PIN>
   <PIN pinname="Units" slicecount="1" values="||">
   </PIN>
   <PIN pinname="Precision" slicecount="1" values="4">
   </PIN>
   <PIN pinname="Value Type" slicecount="1" values="Integer">
   </PIN>
   </NODE>
   <NODE id="105" nodename="IOBox (String)" componentmode="InABox" systemname="IOBox (String)" hiddenwhenlocked="0" managers="">
   <BOUNDS type="Node" left="17745" top="9300" width="480" height="270">
   </BOUNDS>
   <BOUNDS type="Box" left="17745" top="9300" width="480" height="450">
   </BOUNDS>
   <PIN pinname="Input String" visible="0" slicecount="1" pintype="Input" values="|Send&cr;&lf;v|">
   </PIN>
   <PIN pinname="Output String" visible="0" pintype="Output">
   </PIN>
   <PIN pinname="Show Grid" slicecount="1" pintype="Configuration" values="0">
   </PIN>
   <PIN pinname="String Type" slicecount="1" pintype="Configuration" values="MultiLine">
   </PIN>
   <BOUNDS type="Window" left="0" top="0" width="0" height="0">
   </BOUNDS>
   <PIN pinname="Descriptive Name" pintype="Configuration" slicecount="1" values="||">
   </PIN>
   <PIN pinname="Tag" pintype="Configuration" slicecount="1" values="||">
   </PIN>
   <PIN pinname="Pin Visibility" pintype="Configuration" slicecount="1" values="True">
   </PIN>
   <PIN pinname="SliceCount Mode" pintype="Configuration" slicecount="1" values="Input">
   </PIN>
   <PIN pinname="Columns" pintype="Configuration" slicecount="1" values="1">
   </PIN>
   <PIN pinname="Rows" pintype="Configuration" slicecount="1" values="1">
   </PIN>
   <PIN pinname="Pages" pintype="Configuration" slicecount="1" values="1">
   </PIN>
   <PIN pinname="Show SliceIndex" pintype="Configuration" slicecount="1" values="0">
   </PIN>
   <PIN pinname="Font" pintype="Configuration" slicecount="1" values="|Lucida Sans Unicode|">
   </PIN>
   <PIN pinname="Size" pintype="Configuration" slicecount="1" values="7">
   </PIN>
   <PIN pinname="Default" pintype="Configuration" slicecount="1" values="||">
   </PIN>
   <PIN pinname="File Mask" pintype="Configuration" slicecount="1" values="||">
   </PIN>
   <PIN pinname="Maximum Characters" pintype="Configuration" slicecount="1" values="-1">
   </PIN>
   <PIN pinname="Show Characters [#0..#32,#127]" pintype="Configuration" slicecount="1" values="0">
   </PIN>
   <PIN pinname="SliceOffset" pintype="Input" visible="-1" slicecount="1" values="0">
   </PIN>
   <PIN pinname="Changed" pintype="Output" visible="-1">
   </PIN>
   <PIN pinname="ID" pintype="Output" visible="-1">
   </PIN>
   </NODE>
   <NODE systemname="OSCEncoder (Network)" nodename="OSCEncoder (Network)" componentmode="Hidden" id="104">
   <BOUNDS type="Node" left="17460" top="8955" width="100" height="100">
   </BOUNDS>
   <PIN pinname="Address" visible="1" slicecount="3" values="/magi/layer0/loop/select/move,/magi/layer0/fft/bucket,/magi/layer0/fft/beat">
   </PIN>
   <PIN pinname="Type Tags" visible="1" slicecount="1" values="||">
   </PIN>
   <PIN pinname="OSCMessage" visible="1">
   </PIN>
   <PIN pinname="Arguments" visible="1" slicecount="1" values="1">
   </PIN>
   <PIN pinname="Spread as Bundle" slicecount="1" values="0">
   </PIN>
   </NODE>
   <NODE nodename="IOBox (String)" componentmode="InABox" id="103" systemname="IOBox (String)">
   <BOUNDS type="Box" left="15720" top="7545" width="1155" height="240">
   </BOUNDS>
   <BOUNDS type="Node" left="15720" top="7545" width="0" height="0">
   </BOUNDS>
   <PIN pinname="Input String" slicecount="1" visible="1" values="/magi">
   </PIN>
   <PIN pinname="Default" slicecount="1" values="text">
   </PIN>
   <PIN pinname="File Mask" slicecount="1" values="||">
   </PIN>
   <PIN pinname="Maximum Characters" slicecount="1" values="-1">
   </PIN>
   <PIN pinname="Output String" visible="1">
   </PIN>
   </NODE>
   <NODE systemname="Change (Animation)" nodename="Change (Animation)" componentmode="Hidden" id="102">
   <BOUNDS type="Node" left="19965" top="8475" width="100" height="100">
   </BOUNDS>
   <PIN pinname="Input" visible="1" slicecount="2" values="0,0">
   </PIN>
   <PIN pinname="OnChange" visible="1">
   </PIN>
   </NODE>
   <NODE systemname="R (String)" nodename="R (String)" componentmode="Hidden" id="101">
   <BOUNDS type="Node" left="19620" top="9630" width="100" height="100">
   </BOUNDS>
   <PIN pinname="Receive String" slicecount="1" values="host">
   </PIN>
   <PIN pinname="Input Value" visible="1">
   </PIN>
   </NODE>
   <NODE nodename="IOBox (String)" componentmode="InABox" id="100" systemname="IOBox (String)">
   <BOUNDS type="Box" left="17025" top="7470" width="795" height="240">
   </BOUNDS>
   <BOUNDS type="Node" left="17025" top="7470" width="0" height="0">
   </BOUNDS>
   <PIN pinname="Input String" slicecount="1" visible="1" values="||">
   </PIN>
   <PIN pinname="Default" slicecount="1" values="text">
   </PIN>
   <PIN pinname="File Mask" slicecount="1" values="||">
   </PIN>
   <PIN pinname="Maximum Characters" slicecount="1" values="-1">
   </PIN>
   <PIN pinname="Output String" visible="1">
   </PIN>
   </NODE>
   <NODE systemname="Add (String)" nodename="Add (String)" componentmode="Hidden" id="99">
   <BOUNDS type="Node" left="17505" top="8175" width="100" height="100">
   </BOUNDS>
   <PIN pinname="Input Count" slicecount="1" values="3">
   </PIN>
   <PIN pinname="Input 3" visible="1" slicecount="3" values="loopreverse,looppause,loopplay">
   </PIN>
   </NODE>
   <NODE systemname="TogEdge (Animation)" nodename="TogEdge (Animation)" componentmode="Hidden" id="98">
   <BOUNDS type="Node" left="20010" top="9000" width="100" height="100">
   </BOUNDS>
   <PIN pinname="Input" visible="1">
   </PIN>
   <PIN pinname="Up Edge" visible="1">
   </PIN>
   </NODE>
   <NODE nodename="IOBox (String)" componentmode="InABox" id="96" systemname="IOBox (String)">
   <BOUNDS type="Box" left="18105" top="7380" width="1320" height="585">
   </BOUNDS>
   <BOUNDS type="Node" left="18105" top="7380" width="0" height="0">
   </BOUNDS>
   <PIN pinname="Input String" slicecount="2" visible="1" values="/loop/set/cur/a,/loop/set/cur/b">
   </PIN>
   <PIN pinname="Default" slicecount="1" values="text">
   </PIN>
   <PIN pinname="File Mask" slicecount="1" values="||">
   </PIN>
   <PIN pinname="Maximum Characters" slicecount="1" values="-1">
   </PIN>
   <PIN pinname="SliceCount Mode" slicecount="1" values="ColsRowsPages">
   </PIN>
   <PIN pinname="Rows" slicecount="1" values="2">
   </PIN>
   </NODE>
   <NODE nodename="IOBox (String)" componentmode="InABox" id="94" systemname="IOBox (String)">
   <BOUNDS type="Box" left="17865" top="8460" width="795" height="240">
   </BOUNDS>
   <BOUNDS type="Node" left="17865" top="8460" width="0" height="0">
   </BOUNDS>
   <PIN pinname="Input String" slicecount="1" visible="1" values="s">
   </PIN>
   <PIN pinname="Default" slicecount="1" values="||">
   </PIN>
   <PIN pinname="File Mask" slicecount="1" values="||">
   </PIN>
   <PIN pinname="Maximum Characters" slicecount="1" values="-1">
   </PIN>
   </NODE>
   <NODE nodename="IOBox (Value Advanced)" componentmode="InABox" id="93" systemname="IOBox (Value Advanced)">
   <BOUNDS type="Box" left="18165" top="9825" width="480" height="480">
   </BOUNDS>
   <BOUNDS type="Node" left="18165" top="9825" width="0" height="0">
   </BOUNDS>
   <PIN pinname="Units" slicecount="1" values="||">
   </PIN>
   <PIN pinname="Precision" slicecount="1" values="4">
   </PIN>
   <PIN pinname="Value Type" slicecount="1" values="Boolean">
   </PIN>
   <PIN pinname="Behavior" slicecount="1" values="Bang">
   </PIN>
   <PIN pinname="Rows" slicecount="1" values="2">
   </PIN>
   </NODE>
   <LINK srcnodeid="99" srcpinname="Output" dstnodeid="104" dstpinname="Address">
   </LINK>
   <LINK srcnodeid="94" srcpinname="Output String" dstnodeid="104" dstpinname="Type Tags">
   </LINK>
   <LINK srcnodeid="104" srcpinname="OSCMessage" dstnodeid="107" dstpinname="Input">
   </LINK>
   <LINK srcnodeid="98" srcpinname="Up Edge" dstnodeid="107" dstpinname="Do Send">
   </LINK>
   <LINK srcnodeid="101" srcpinname="Input Value" dstnodeid="107" dstpinname="Remote Host">
   </LINK>
   <LINK srcnodeid="106" srcpinname="Y Output Value" dstnodeid="107" dstpinname="Remote Port">
   </LINK>
   <LINK srcnodeid="103" srcpinname="Output String" dstnodeid="99" dstpinname="Input 1">
   </LINK>
   <LINK srcnodeid="100" srcpinname="Output String" dstnodeid="99" dstpinname="Input 2">
   </LINK>
   <LINK srcnodeid="96" srcpinname="Output String" dstnodeid="99" dstpinname="Input 3">
   </LINK>
   <LINK srcnodeid="98" srcpinname="Up Edge" dstnodeid="93" dstpinname="Y Input Value">
   </LINK>
   <LINK srcnodeid="102" srcpinname="OnChange" dstnodeid="98" dstpinname="Input">
   </LINK>
   <LINK srcnodeid="55" srcpinname="Output String" dstnodeid="100" dstpinname="Input String">
   </LINK>
   <NODE id="72" nodename="IOBox (String)" componentmode="InABox" systemname="IOBox (String)">
   <BOUNDS type="Box" left="11370" top="10650" width="1560" height="270">
   </BOUNDS>
   <BOUNDS type="Node" left="11370" top="10650" width="0" height="0">
   </BOUNDS>
   <PIN pinname="Input String" slicecount="1" visible="1" values="/loop/select/move">
   </PIN>
   <PIN pinname="Default" slicecount="1" values="text">
   </PIN>
   <PIN pinname="File Mask" slicecount="1" values="||">
   </PIN>
   <PIN pinname="Maximum Characters" slicecount="1" values="-1">
   </PIN>
   </NODE>
   <NODE id="71" systemname="Add (String)" nodename="Add (String)" componentmode="Hidden">
   <BOUNDS type="Node" left="10620" top="11445" width="100" height="100">
   </BOUNDS>
   <PIN pinname="Input Count" slicecount="1" values="3">
   </PIN>
   <PIN pinname="Input 3" visible="1" slicecount="1" values="text">
   </PIN>
   <PIN pinname="Input 2" slicecount="1" visible="1" values="/layer0">
   </PIN>
   </NODE>
   <NODE id="69" systemname="R (String)" nodename="R (String)" componentmode="Hidden">
   <BOUNDS type="Node" left="15195" top="11775" width="100" height="100">
   </BOUNDS>
   <PIN pinname="Receive String" slicecount="1" values="host">
   </PIN>
   <PIN pinname="Input Value" visible="1">
   </PIN>
   </NODE>
   <NODE id="67" nodename="IOBox (String)" componentmode="InABox" systemname="IOBox (String)">
   <BOUNDS type="Box" left="9585" top="10770" width="1155" height="240">
   </BOUNDS>
   <BOUNDS type="Node" left="9585" top="10770" width="0" height="0">
   </BOUNDS>
   <PIN pinname="Input String" slicecount="1" visible="1" values="/magi">
   </PIN>
   <PIN pinname="Default" slicecount="1" values="text">
   </PIN>
   <PIN pinname="File Mask" slicecount="1" values="||">
   </PIN>
   <PIN pinname="Maximum Characters" slicecount="1" values="-1">
   </PIN>
   <PIN pinname="Output String" visible="1">
   </PIN>
   </NODE>
   <NODE id="66" nodename="IOBox (String)" componentmode="InABox" systemname="IOBox (String)">
   <BOUNDS type="Box" left="13335" top="10665" width="285" height="240">
   </BOUNDS>
   <BOUNDS type="Node" left="13335" top="10665" width="0" height="0">
   </BOUNDS>
   <PIN pinname="Input String" slicecount="1" visible="1" values="s">
   </PIN>
   <PIN pinname="Default" slicecount="1" values="||">
   </PIN>
   <PIN pinname="File Mask" slicecount="1" values="||">
   </PIN>
   <PIN pinname="Maximum Characters" slicecount="1" values="-1">
   </PIN>
   </NODE>
   <NODE id="65" systemname="OSCEncoder (Network)" nodename="OSCEncoder (Network)" componentmode="Hidden">
   <PIN pinname="Arguments" slicecount="3" visible="1" values="1,0,1">
   </PIN>
   <BOUNDS type="Node" left="13035" top="11100" width="100" height="100">
   </BOUNDS>
   <PIN pinname="Address" visible="1" slicecount="3" values="/magi/layer0/loop/select/move,/magi/layer0/fft/bucket,/magi/layer0/fft/beat">
   </PIN>
   <PIN pinname="Type Tags" visible="1">
   </PIN>
   <PIN pinname="OSCMessage" visible="1">
   </PIN>
   <PIN pinname="Spread as Bundle" slicecount="1" values="0">
   </PIN>
   </NODE>
   <NODE id="64" nodename="IOBox (String)" componentmode="InABox" systemname="IOBox (String)" hiddenwhenlocked="0" managers="">
   <BOUNDS type="Node" left="13320" top="11445" width="480" height="270">
   </BOUNDS>
   <BOUNDS type="Box" left="13320" top="11445" width="480" height="450">
   </BOUNDS>
   <PIN pinname="Input String" visible="0" slicecount="1" pintype="Input" values="|Send&cr;&lf;v|">
   </PIN>
   <PIN pinname="Output String" visible="0" pintype="Output">
   </PIN>
   <PIN pinname="Show Grid" slicecount="1" pintype="Configuration" values="0">
   </PIN>
   <PIN pinname="String Type" slicecount="1" pintype="Configuration" values="MultiLine">
   </PIN>
   <BOUNDS type="Window" left="0" top="0" width="0" height="0">
   </BOUNDS>
   <PIN pinname="Descriptive Name" pintype="Configuration" slicecount="1" values="||">
   </PIN>
   <PIN pinname="Tag" pintype="Configuration" slicecount="1" values="||">
   </PIN>
   <PIN pinname="Pin Visibility" pintype="Configuration" slicecount="1" values="True">
   </PIN>
   <PIN pinname="SliceCount Mode" pintype="Configuration" slicecount="1" values="Input">
   </PIN>
   <PIN pinname="Columns" pintype="Configuration" slicecount="1" values="1">
   </PIN>
   <PIN pinname="Rows" pintype="Configuration" slicecount="1" values="1">
   </PIN>
   <PIN pinname="Pages" pintype="Configuration" slicecount="1" values="1">
   </PIN>
   <PIN pinname="Show SliceIndex" pintype="Configuration" slicecount="1" values="0">
   </PIN>
   <PIN pinname="Font" pintype="Configuration" slicecount="1" values="|Lucida Sans Unicode|">
   </PIN>
   <PIN pinname="Size" pintype="Configuration" slicecount="1" values="7">
   </PIN>
   <PIN pinname="Default" pintype="Configuration" slicecount="1" values="||">
   </PIN>
   <PIN pinname="File Mask" pintype="Configuration" slicecount="1" values="||">
   </PIN>
   <PIN pinname="Maximum Characters" pintype="Configuration" slicecount="1" values="-1">
   </PIN>
   <PIN pinname="Show Characters [#0..#32,#127]" pintype="Configuration" slicecount="1" values="0">
   </PIN>
   <PIN pinname="SliceOffset" pintype="Input" visible="-1" slicecount="1" values="0">
   </PIN>
   <PIN pinname="Changed" pintype="Output" visible="-1">
   </PIN>
   <PIN pinname="ID" pintype="Output" visible="-1">
   </PIN>
   </NODE>
   <NODE id="63" nodename="IOBox (Value Advanced)" componentmode="InABox" systemname="IOBox (Value Advanced)">
   <BOUNDS type="Box" left="14970" top="12210" width="795" height="240">
   </BOUNDS>
   <BOUNDS type="Node" left="14970" top="12210" width="0" height="0">
   </BOUNDS>
   <PIN pinname="Y Input Value" slicecount="1" values="7001">
   </PIN>
   <PIN pinname="Units" slicecount="1" values="||">
   </PIN>
   <PIN pinname="Precision" slicecount="1" values="4">
   </PIN>
   <PIN pinname="Value Type" slicecount="1" values="Integer">
   </PIN>
   </NODE>
   <NODE id="61" systemname="UDP (Network Client)" nodename="UDP (Network Client)" componentmode="Hidden">
   <PIN pinname="Do Send" slicecount="2" values="0,0">
   </PIN>
   <BOUNDS type="Node" left="13080" top="12465" width="1485" height="270">
   </BOUNDS>
   <PIN pinname="Input" visible="1" slicecount="1" values="||">
   </PIN>
   <PIN pinname="Remote Host" slicecount="1" visible="1" values="192.168.0.103">
   </PIN>
   </NODE>
   <LINK srcnodeid="63" srcpinname="Y Output Value" dstnodeid="61" dstpinname="Remote Port">
   </LINK>
   <LINK srcnodeid="69" srcpinname="Input Value" dstnodeid="61" dstpinname="Remote Host">
   </LINK>
   <LINK srcnodeid="65" srcpinname="OSCMessage" dstnodeid="61" dstpinname="Input">
   </LINK>
   <LINK srcnodeid="66" srcpinname="Output String" dstnodeid="65" dstpinname="Type Tags">
   </LINK>
   <LINK srcnodeid="71" srcpinname="Output" dstnodeid="65" dstpinname="Address">
   </LINK>
   <LINK srcnodeid="67" srcpinname="Output String" dstnodeid="71" dstpinname="Input 1">
   </LINK>
   <LINK srcnodeid="55" srcpinname="Output String" dstnodeid="71" dstpinname="Input 2">
   </LINK>
   <LINK srcnodeid="72" srcpinname="Output String" dstnodeid="71" dstpinname="Input 3">
   </LINK>
   <NODE id="62" nodename="IOBox (Value Advanced)" componentmode="InABox" systemname="IOBox (Value Advanced)">
   <PIN pinname="Y Input Value" slicecount="1" visible="1" values="1">
   </PIN>
   <BOUNDS type="Box" left="14175" top="11520" width="480" height="480">
   </BOUNDS>
   <BOUNDS type="Node" left="14175" top="11520" width="0" height="0">
   </BOUNDS>
   <PIN pinname="Units" slicecount="1" values="||">
   </PIN>
   <PIN pinname="Precision" slicecount="1" values="4">
   </PIN>
   <PIN pinname="Value Type" slicecount="1" values="Boolean">
   </PIN>
   <PIN pinname="Behavior" slicecount="1" values="Bang">
   </PIN>
   <PIN pinname="X Input Value" slicecount="1" values="0">
   </PIN>
   <PIN pinname="Columns" slicecount="1" values="2">
   </PIN>
   </NODE>
   <LINK srcnodeid="62" srcpinname="Y Output Value" dstnodeid="61" dstpinname="Do Send">
   </LINK>
   <NODE id="68" systemname="Change (Animation)" nodename="Change (Animation)" componentmode="Hidden">
   <BOUNDS type="Node" left="15180" top="11175" width="100" height="100">
   </BOUNDS>
   <PIN pinname="Input" visible="1" slicecount="2" values="0,0">
   </PIN>
   <PIN pinname="OnChange" visible="1">
   </PIN>
   </NODE>
   <LINK srcnodeid="68" srcpinname="OnChange" dstnodeid="62" dstpinname="Y Input Value">
   </LINK>
   <NODE id="74" nodename="IOBox (String)" componentmode="InABox" systemname="IOBox (String)">
   <BOUNDS type="Box" left="15555" top="10095" width="810" height="705">
   </BOUNDS>
   <BOUNDS type="Node" left="15555" top="10095" width="0" height="0">
   </BOUNDS>
   <PIN pinname="Input String" slicecount="2" visible="1" values="-1,1">
   </PIN>
   <PIN pinname="Default" slicecount="1" values="||">
   </PIN>
   <PIN pinname="File Mask" slicecount="1" values="||">
   </PIN>
   <PIN pinname="Maximum Characters" slicecount="1" values="-1">
   </PIN>
   <PIN pinname="String Type" slicecount="1" values="MultiLine">
   </PIN>
   <PIN pinname="Rows" slicecount="1" values="2">
   </PIN>
   <PIN pinname="SliceCount Mode" slicecount="1" values="ColsRowsPages">
   </PIN>
   </NODE>
   <NODE id="73" systemname="Select (String)" nodename="Select (String)" componentmode="Hidden">
   <BOUNDS type="Node" left="14400" top="10650" width="100" height="100">
   </BOUNDS>
   <PIN pinname="Output" visible="1">
   </PIN>
   <PIN pinname="Select" visible="1" slicecount="2" values="0,0">
   </PIN>
   <PIN pinname="Input" visible="1">
   </PIN>
   </NODE>
   <LINK srcnodeid="74" srcpinname="Output String" dstnodeid="73" dstpinname="Input">
   </LINK>
   <LINK srcnodeid="73" srcpinname="Output" dstnodeid="65" dstpinname="Arguments">
   </LINK>
   <LINK srcnodeid="12" srcpinname="Touched" dstnodeid="102" dstpinname="Input">
   </LINK>
   <NODE nodename="IOBox (String)" componentmode="InABox" id="108" systemname="IOBox (String)">
   <BOUNDS type="Node" left="11340" top="10095" width="2730" height="270">
   </BOUNDS>
   <BOUNDS type="Box" left="11340" top="10095" width="2730" height="270">
   </BOUNDS>
   <PIN pinname="Input String" visible="0" slicecount="1" values="|/ not used but useful to have i guess|">
   </PIN>
   <PIN pinname="Output String" visible="0">
   </PIN>
   <PIN pinname="Show Grid" slicecount="1" values="0">
   </PIN>
   <PIN pinname="String Type" slicecount="1" values="MultiLine">
   </PIN>
   </NODE>
   <NODE nodename="IOBox (Value Advanced)" componentmode="InABox" id="113" systemname="IOBox (Value Advanced)">
   <BOUNDS type="Box" left="9120" top="765" width="795" height="240">
   </BOUNDS>
   <BOUNDS type="Node" left="9120" top="765" width="0" height="0">
   </BOUNDS>
   <PIN pinname="Y Input Value" slicecount="1" visible="1" values="0.08275">
   </PIN>
   <PIN pinname="Units" slicecount="1" values="||">
   </PIN>
   <PIN pinname="Precision" slicecount="1" values="4">
   </PIN>
   </NODE>
   <LINK srcnodeid="113" srcpinname="Y Output Value" dstnodeid="78" dstpinname="Input 2">
   </LINK>
   <NODE nodename="IOBox (Value Advanced)" componentmode="InABox" id="114" systemname="IOBox (Value Advanced)">
   <BOUNDS type="Box" left="5265" top="1875" width="795" height="240">
   </BOUNDS>
   <BOUNDS type="Node" left="5265" top="1875" width="0" height="0">
   </BOUNDS>
   <PIN pinname="Y Input Value" slicecount="1" visible="1" values="0.2835">
   </PIN>
   <PIN pinname="Units" slicecount="1" values="||">
   </PIN>
   <PIN pinname="Precision" slicecount="1" values="4">
   </PIN>
   </NODE>
   <LINK srcnodeid="114" srcpinname="Y Output Value" dstnodeid="8" dstpinname="ScaleX">
   </LINK>
   <NODE systemname="FormatValue (String)" nodename="FormatValue (String)" componentmode="Hidden" id="115">
   <BOUNDS type="Node" left="5190" top="7320" width="100" height="100">
   </BOUNDS>
   <PIN pinname="Input" visible="1">
   </PIN>
   <PIN pinname="Output" visible="1">
   </PIN>
   </NODE>
   <LINK srcnodeid="59" srcpinname="X" dstnodeid="115" dstpinname="Input">
   </LINK>
   <LINK srcnodeid="115" srcpinname="Output" dstnodeid="60" dstpinname="Input 1">
   </LINK>
   <LINK srcnodeid="50" srcpinname="OnChange" dstnodeid="45" dstpinname="Y Input Value">
   </LINK>
   <NODE systemname="AsValue (String)" nodename="AsValue (String)" componentmode="Hidden" id="118">
   <BOUNDS type="Node" left="14880" top="750" width="100" height="100">
   </BOUNDS>
   <PIN pinname="Input" visible="1">
   </PIN>
   <PIN pinname="Output" visible="1">
   </PIN>
   </NODE>
   <NODE nodename="IOBox (String)" componentmode="InABox" id="119" systemname="IOBox (String)">
   <BOUNDS type="Box" left="14895" top="60" width="795" height="240">
   </BOUNDS>
   <BOUNDS type="Node" left="14895" top="60" width="0" height="0">
   </BOUNDS>
   <PIN pinname="Input String" slicecount="1" visible="1" values="||">
   </PIN>
   <PIN pinname="Default" slicecount="1" values="||">
   </PIN>
   <PIN pinname="File Mask" slicecount="1" values="||">
   </PIN>
   <PIN pinname="Maximum Characters" slicecount="1" values="-1">
   </PIN>
   <PIN pinname="String Type" slicecount="1" values="MultiLine">
   </PIN>
   <PIN pinname="Descriptive Name" slicecount="1" values="osc_inp">
   </PIN>
   <PIN pinname="Output String" visible="1">
   </PIN>
   </NODE>
   <LINK srcnodeid="119" srcpinname="Output String" dstnodeid="118" dstpinname="Input">
   </LINK>
   <NODE nodename="IOBox (String)" componentmode="InABox" id="120" systemname="IOBox (String)">
   <BOUNDS type="Box" left="17025" top="900" width="1635" height="375">
   </BOUNDS>
   <BOUNDS type="Node" left="17025" top="900" width="0" height="0">
   </BOUNDS>
   <PIN pinname="Input String" slicecount="1" visible="1" values="||">
   </PIN>
   <PIN pinname="Default" slicecount="1" values="||">
   </PIN>
   <PIN pinname="File Mask" slicecount="1" values="||">
   </PIN>
   <PIN pinname="Maximum Characters" slicecount="1" values="-1">
   </PIN>
   <PIN pinname="String Type" slicecount="1" values="MultiLine">
   </PIN>
   <PIN pinname="Descriptive Name" slicecount="1" values="osc_addr">
   </PIN>
   <PIN pinname="Output String" visible="1">
   </PIN>
   </NODE>
   <NODE systemname="Find (String)" nodename="Find (String)" componentmode="Hidden" id="121">
   <BOUNDS type="Node" left="17250" top="2745" width="100" height="100">
   </BOUNDS>
   <PIN pinname="Occurence Mode" slicecount="1" values="All">
   </PIN>
   <PIN pinname="Input" visible="1">
   </PIN>
   <PIN pinname="Substring" visible="1">
   </PIN>
   <PIN pinname="Count" visible="1">
   </PIN>
   </NODE>
   <LINK srcnodeid="120" srcpinname="Output String" dstnodeid="121" dstpinname="Input">
   </LINK>
   <NODE nodename="IOBox (String)" componentmode="InABox" id="122" systemname="IOBox (String)">
   <BOUNDS type="Box" left="18450" top="1905" width="795" height="240">
   </BOUNDS>
   <BOUNDS type="Node" left="18450" top="1905" width="0" height="0">
   </BOUNDS>
   <PIN pinname="Input String" slicecount="1" visible="1" values="on_off">
   </PIN>
   <PIN pinname="Default" slicecount="1" values="||">
   </PIN>
   <PIN pinname="File Mask" slicecount="1" values="||">
   </PIN>
   <PIN pinname="Maximum Characters" slicecount="1" values="-1">
   </PIN>
   </NODE>
   <LINK srcnodeid="122" srcpinname="Output String" dstnodeid="121" dstpinname="Substring">
   </LINK>
   <NODE systemname="GT (Value)" nodename="GT (Value)" componentmode="Hidden" id="123">
   <BOUNDS type="Node" left="17250" top="3255" width="100" height="100">
   </BOUNDS>
   <PIN pinname="Input 1" visible="1" slicecount="3" values="1,0,0">
   </PIN>
   <PIN pinname="Output" visible="1">
   </PIN>
   </NODE>
   <NODE nodename="IOBox (Value Advanced)" componentmode="InABox" id="127" systemname="IOBox (Value Advanced)">
   <BOUNDS type="Box" left="16095" top="4830" width="555" height="945">
   </BOUNDS>
   <BOUNDS type="Node" left="16095" top="4830" width="0" height="0">
   </BOUNDS>
   <PIN pinname="Units" slicecount="1" values="||">
   </PIN>
   <PIN pinname="Precision" slicecount="1" values="4">
   </PIN>
   <PIN pinname="Value Type" slicecount="1" values="Boolean">
   </PIN>
   <PIN pinname="Behavior" slicecount="1" values="Toggle">
   </PIN>
   <PIN pinname="Rows" slicecount="1" values="2">
   </PIN>
   <PIN pinname="Y Input Value" visible="1" slicecount="2" values="0,0">
   </PIN>
   <PIN pinname="Y Output Value" visible="1">
   </PIN>
   </NODE>
   <NODE systemname="Find (String)" nodename="Find (String)" componentmode="Hidden" id="128">
   <BOUNDS type="Node" left="18105" top="2820" width="100" height="100">
   </BOUNDS>
   <PIN pinname="Occurence Mode" slicecount="1" values="All">
   </PIN>
   <PIN pinname="Input" visible="1" slicecount="1" values="||">
   </PIN>
   <PIN pinname="Substring" visible="1" slicecount="1" values="||">
   </PIN>
   <PIN pinname="Count" visible="1">
   </PIN>
   </NODE>
   <LINK srcnodeid="120" srcpinname="Output String" dstnodeid="128" dstpinname="Input">
   </LINK>
   <NODE nodename="IOBox (String)" componentmode="InABox" id="129" systemname="IOBox (String)">
   <BOUNDS type="Box" left="19590" top="2205" width="795" height="240">
   </BOUNDS>
   <BOUNDS type="Node" left="19590" top="2205" width="0" height="0">
   </BOUNDS>
   <PIN pinname="Input String" slicecount="1" visible="1" values="type">
   </PIN>
   <PIN pinname="Default" slicecount="1" values="||">
   </PIN>
   <PIN pinname="File Mask" slicecount="1" values="||">
   </PIN>
   <PIN pinname="Maximum Characters" slicecount="1" values="-1">
   </PIN>
   </NODE>
   <LINK srcnodeid="129" srcpinname="Output String" dstnodeid="128" dstpinname="Substring">
   </LINK>
   <NODE systemname="Cons (Spreads)" filename="%VVVV%\lib\nodes\plugins\VVVV.Nodes.dll" nodename="Cons (Spreads)" componentmode="Hidden" id="133">
   <BOUNDS type="Node" left="17145" top="4530" width="100" height="100">
   </BOUNDS>
   <PIN pinname="Input 2" visible="1" slicecount="1" values="0">
   </PIN>
   <PIN pinname="Input 1" visible="1" slicecount="3" values="0.059358824044466,0,0">
   </PIN>
   <PIN pinname="Output" visible="1">
   </PIN>
   </NODE>
   <LINK srcnodeid="133" srcpinname="Output" dstnodeid="127" dstpinname="Y Input Value">
   </LINK>
   <NODE systemname="GT (Value)" nodename="GT (Value)" componentmode="Hidden" id="134">
   <BOUNDS type="Node" left="18015" top="3360" width="100" height="100">
   </BOUNDS>
   <PIN pinname="Input 1" visible="1" slicecount="3" values="1,0,0">
   </PIN>
   <PIN pinname="Output" visible="1">
   </PIN>
   </NODE>
   <LINK srcnodeid="128" srcpinname="Count" dstnodeid="134" dstpinname="Input 1">
   </LINK>
   <LINK srcnodeid="121" srcpinname="Count" dstnodeid="123" dstpinname="Input 1">
   </LINK>
   <NODE systemname="Select (Value)" filename="%VVVV%\lib\nodes\plugins\VVVV.Nodes.dll" nodename="Select (Value)" componentmode="Hidden" id="135">
   <BOUNDS type="Node" left="16695" top="3870" width="100" height="100">
   </BOUNDS>
   <PIN pinname="Input" visible="1">
   </PIN>
   <PIN pinname="Select" visible="1">
   </PIN>
   <PIN pinname="Output" visible="1">
   </PIN>
   </NODE>
   <LINK srcnodeid="118" srcpinname="Output" dstnodeid="135" dstpinname="Input">
   </LINK>
   <LINK srcnodeid="123" srcpinname="Output" dstnodeid="135" dstpinname="Select">
   </LINK>
   <LINK srcnodeid="135" srcpinname="Output" dstnodeid="133" dstpinname="Input 1">
   </LINK>
   <NODE systemname="Select (Value)" filename="%VVVV%\lib\nodes\plugins\VVVV.Nodes.dll" nodename="Select (Value)" componentmode="Hidden" id="137">
   <BOUNDS type="Node" left="17580" top="3930" width="100" height="100">
   </BOUNDS>
   <PIN pinname="Input" visible="1" slicecount="1" values="0">
   </PIN>
   <PIN pinname="Select" visible="1" slicecount="1" values="0">
   </PIN>
   <PIN pinname="Output" visible="1">
   </PIN>
   </NODE>
   <LINK srcnodeid="118" srcpinname="Output" dstnodeid="137" dstpinname="Input">
   </LINK>
   <LINK srcnodeid="134" srcpinname="Output" dstnodeid="137" dstpinname="Select">
   </LINK>
   <LINK srcnodeid="137" srcpinname="Output" dstnodeid="133" dstpinname="Input 2">
   </LINK>
   <LINK srcnodeid="127" srcpinname="Y Output Value" dstnodeid="4" dstpinname="Value Input">
   </LINK>
   <NODE nodename="IOBox (Value Advanced)" componentmode="InABox" id="138" systemname="IOBox (Value Advanced)">
   <BOUNDS type="Box" left="7050" top="5670" width="480" height="480">
   </BOUNDS>
   <BOUNDS type="Node" left="7050" top="5670" width="0" height="0">
   </BOUNDS>
   <PIN pinname="Units" slicecount="1" values="||">
   </PIN>
   <PIN pinname="Precision" slicecount="1" values="4">
   </PIN>
   <PIN pinname="Value Type" slicecount="1" values="Boolean">
   </PIN>
   <PIN pinname="Behavior" slicecount="1" values="Press">
   </PIN>
   <PIN pinname="Rows" slicecount="1" values="2">
   </PIN>
   </NODE>
   <LINK srcnodeid="4" srcpinname="Hit" dstnodeid="138" dstpinname="Y Input Value">
   </LINK>
   <NODE systemname="Find (String)" nodename="Find (String)" componentmode="Hidden" id="141">
   <BOUNDS type="Node" left="18660" top="3270" width="100" height="100">
   </BOUNDS>
   <PIN pinname="Occurence Mode" slicecount="1" values="All">
   </PIN>
   <PIN pinname="Input" visible="1" slicecount="1" values="||">
   </PIN>
   <PIN pinname="Substring" visible="1" slicecount="1" values="||">
   </PIN>
   <PIN pinname="Count" visible="1">
   </PIN>
   </NODE>
   <NODE nodename="IOBox (String)" componentmode="InABox" id="140" systemname="IOBox (String)">
   <BOUNDS type="Box" left="20145" top="2655" width="795" height="240">
   </BOUNDS>
   <BOUNDS type="Node" left="20145" top="2655" width="0" height="0">
   </BOUNDS>
   <PIN pinname="Input String" slicecount="1" visible="1" values="cur_range">
   </PIN>
   <PIN pinname="Default" slicecount="1" values="||">
   </PIN>
   <PIN pinname="File Mask" slicecount="1" values="||">
   </PIN>
   <PIN pinname="Maximum Characters" slicecount="1" values="-1">
   </PIN>
   </NODE>
   <LINK srcnodeid="140" srcpinname="Output String" dstnodeid="141" dstpinname="Substring">
   </LINK>
   <NODE systemname="GT (Value)" nodename="GT (Value)" componentmode="Hidden" id="139">
   <BOUNDS type="Node" left="18570" top="3810" width="100" height="100">
   </BOUNDS>
   <PIN pinname="Input 1" visible="1" slicecount="3" values="1,0,0">
   </PIN>
   <PIN pinname="Output" visible="1">
   </PIN>
   </NODE>
   <LINK srcnodeid="141" srcpinname="Count" dstnodeid="139" dstpinname="Input 1">
   </LINK>
   <LINK srcnodeid="120" srcpinname="Output String" dstnodeid="141" dstpinname="Input">
   </LINK>
   <NODE systemname="Select (String)" nodename="Select (String)" componentmode="Hidden" id="145">
   <BOUNDS type="Node" left="18900" top="4485" width="100" height="100">
   </BOUNDS>
   <PIN pinname="Input" visible="1">
   </PIN>
   <PIN pinname="Select" visible="1">
   </PIN>
   <PIN pinname="Output" visible="1">
   </PIN>
   </NODE>
   <LINK srcnodeid="119" srcpinname="Output String" dstnodeid="145" dstpinname="Input">
   </LINK>
   <LINK srcnodeid="139" srcpinname="Output" dstnodeid="145" dstpinname="Select">
   </LINK>
   <NODE systemname="Separate (String)" nodename="Separate (String)" componentmode="Hidden" id="146">
   <BOUNDS type="Node" left="18735" top="4995" width="100" height="100">
   </BOUNDS>
   <PIN pinname="Intersperse" slicecount="1" values="Comma">
   </PIN>
   <PIN pinname="Input" visible="1">
   </PIN>
   <PIN pinname="Output" visible="1">
   </PIN>
   </NODE>
   <LINK srcnodeid="145" srcpinname="Output" dstnodeid="146" dstpinname="Input">
   </LINK>
   <NODE systemname="Vector (2d Split)" nodename="Vector (2d Split)" componentmode="Hidden" id="147">
   <BOUNDS type="Node" left="17985" top="5970" width="100" height="100">
   </BOUNDS>
   <PIN pinname="XY" visible="1">
   </PIN>
   <PIN pinname="X" visible="1">
   </PIN>
   <PIN pinname="Y" visible="1">
   </PIN>
   </NODE>
   <NODE systemname="AsValue (String)" nodename="AsValue (String)" componentmode="Hidden" id="148">
   <BOUNDS type="Node" left="17985" top="5535" width="100" height="100">
   </BOUNDS>
   <PIN pinname="Input" visible="1" slicecount="1" values="||">
   </PIN>
   <PIN pinname="Output" visible="1">
   </PIN>
   </NODE>
   <LINK srcnodeid="146" srcpinname="Output" dstnodeid="148" dstpinname="Input">
   </LINK>
   <LINK srcnodeid="148" srcpinname="Output" dstnodeid="147" dstpinname="XY">
   </LINK>
   <NODE nodename="IOBox (Value Advanced)" componentmode="InABox" id="149" systemname="IOBox (Value Advanced)">
   <BOUNDS type="Box" left="17715" top="6510" width="795" height="240">
   </BOUNDS>
   <BOUNDS type="Node" left="17715" top="6510" width="0" height="0">
   </BOUNDS>
   <PIN pinname="Units" slicecount="1" values="||">
   </PIN>
   <PIN pinname="Precision" slicecount="1" values="4">
   </PIN>
   </NODE>
   <LINK srcnodeid="147" srcpinname="X" dstnodeid="149" dstpinname="Y Input Value">
   </LINK>
   <NODE nodename="IOBox (Value Advanced)" componentmode="InABox" id="150" systemname="IOBox (Value Advanced)">
   <BOUNDS type="Box" left="18750" top="6480" width="795" height="240">
   </BOUNDS>
   <BOUNDS type="Node" left="18750" top="6480" width="0" height="0">
   </BOUNDS>
   <PIN pinname="Units" slicecount="1" values="||">
   </PIN>
   <PIN pinname="Precision" slicecount="1" values="4">
   </PIN>
   </NODE>
   <LINK srcnodeid="147" srcpinname="Y" dstnodeid="150" dstpinname="Y Input Value">
   </LINK>
   <LINK srcnodeid="127" srcpinname="Y Output Value" dstnodeid="90" dstpinname="Input">
   </LINK>
   </PATCH>